{
  "creds": {
    "noiseKey": {
      "private": {
        "type": "Buffer",
        "data": "8BDMZG3Bj4HFMqxfYB2fiawJSYBHc4B9aUqVy4ibqEQ="
      },
      "public": {
        "type": "Buffer",
        "data": "GRcd3TS77xVZQRvb6h6sZaTzN+yHfp5ACrop2zO2fSA="
      }
    },
    "signedIdentityKey": {
      "private": {
        "type": "Buffer",
        "data": "0K7qIGP9uYYCa5aNJuKm7H5AgzxYUR5gZb3B8KgYoF4="
      },
      "public": {
        "type": "Buffer",
        "data": "JrF0clNItxWjtDxMqUuNFCtlZzWPPT2Ie2rUs1uOmwQ="
      }
    },
    "signedPreKey": {
      "keyPair": {
        "private": {
          "type": "Buffer",
          "data": "iO7Nq4bxkmKiUYBsjHZ0IqKmxchSOKIZEBHrC37g1W4="
        },
        "public": {
          "type": "Buffer",
          "data": "C1IKIHi/ElQ4xKbGi89CO4KRNl92w3cDiEKuLq++UBU="
        }
      },
      "signature": {
        "type": "Buffer",
        "data": "+gDS3ofbmVcwSJyimvAeGKOYcJfADHhk/kJeiAFPto7t5TYchn/P2CJuwAIBqknKepFep26IJn5IkEgNNQBHhA=="
      },
      "keyId": 1
    },
    "registrationId": 191,
    "advSecretKey": "gPUpARiUkvODHnPVXCPi6pCBn29Cd0qE6aQsHdjQ4bM=",
    "processedHistoryMessages": [
      {
        "key": {
          "remoteJid": "6282122365620@s.whatsapp.net",
          "fromMe": true,
          "id": "DCE3DE90BE5885E5706489593ECC5E02"
        },
        "messageTimestamp": 1662003244
      },
      {
        "key": {
          "remoteJid": "6282122365620@s.whatsapp.net",
          "fromMe": true,
          "id": "0A6A4211D12CDBAF6D37418B00AF2F22"
        },
        "messageTimestamp": 1662003244
      }
    ],
    "nextPreKeyId": 31,
    "firstUnuploadedPreKeyId": 31,
    "accountSyncCounter": 0,
    "accountSettings": {
      "unarchiveChats": false
    },
    "account": {
      "details": "CPae2AYQptDAmAYYAQ==",
      "accountSignatureKey": "rapdu6jMjxN7QrgJJGXFXZA+P6GTGX5aLVNV/IyqTSs=",
      "accountSignature": "VcbBy/guDvzSIPjBKsqTW9OBW42a8CtSuucJ/iOfXuHJIMgMyDmD9aXBor27rKDMzbJoubj4t0GDjh1kK3sBDA==",
      "deviceSignature": "b0wJCOZqTNAwNwkOJ1MU6iOfQK+ywZ6CT/FbF7w7YsYNeQczvL1ljFbK/x6SxWFMh0xeLT5IT2Ftl5mltiOOiQ=="
    },
    "me": {
      "id": "6282122365620:22@s.whatsapp.net",
      "name": "Maoneart Electronic"
    },
    "signalIdentities": [
      {
        "identifier": {
          "name": "6282122365620:22@s.whatsapp.net",
          "deviceId": 0
        },
        "identifierKey": {
          "type": "Buffer",
          "data": "Ba2qXbuozI8Te0K4CSRlxV2QPj+hkxl+Wi1TVfyMqk0r"
        }
      }
    ],
    "platform": "smba",
    "lastAccountSyncTimestamp": 1662003241,
    "myAppStateKeyId": "AAAAANmE"
  },
  "keys": {
    "preKeys": {
      "1": {
        "private": {
          "type": "Buffer",
          "data": "OAKaBF9szgJpD2nME6zYezZ1Zu0F9hk02SBxiuupmk0="
        },
        "public": {
          "type": "Buffer",
          "data": "eud2R3/u/OxBxyXh3s3zRUjp0b6PWk0otYUPZWh0KDg="
        }
      },
      "2": {
        "private": {
          "type": "Buffer",
          "data": "oNYegL+G4JQzkQShHiOmf2k8cLgs3VDmJ8MLC5ZF5Fc="
        },
        "public": {
          "type": "Buffer",
          "data": "D99Co0tUhUCNrIu4VDxACWjPiEP5ME1g5EDk2WKgkmw="
        }
      },
      "3": {
        "private": {
          "type": "Buffer",
          "data": "QK8JXna7EYChqbrefei/Zs5qvVp+U+Nox8uG0P/SlX0="
        },
        "public": {
          "type": "Buffer",
          "data": "OCke+BpUdG43Z4NmfQZGJ2J3UwGSSsl4Z5E59opupkg="
        }
      },
      "4": {
        "private": {
          "type": "Buffer",
          "data": "eOaeBuj7+cnfwnhlv3Nn19qftmAscHKzcbuPucpiUVY="
        },
        "public": {
          "type": "Buffer",
          "data": "NuE9rX1I4InZnoIMfbv5ggcPuDxoCY8MwjsLZZrYa30="
        }
      },
      "5": null,
      "6": {
        "private": {
          "type": "Buffer",
          "data": "2ApnzZW/RkgD4ftCQ7LE9D7Lu4zow/i8tWrPzuaGL1k="
        },
        "public": {
          "type": "Buffer",
          "data": "KyDfBA2G/W1fB2JTlDEeeYqE2E6viKEddeEJ8q7ucks="
        }
      },
      "7": {
        "private": {
          "type": "Buffer",
          "data": "oMiNtHqeRxwvfDtSD54MVNgG6pgH3wB60O+imYXn4GQ="
        },
        "public": {
          "type": "Buffer",
          "data": "HhqE9YoCjInf8WLrnjfmJ6jDNNERlZbzC1T8zA7JfBk="
        }
      },
      "8": {
        "private": {
          "type": "Buffer",
          "data": "IPHwWBhFZ6mQS4X/pOj92GVLfaGZZxbJoXP6VF0Umk8="
        },
        "public": {
          "type": "Buffer",
          "data": "C8rUfNbcWXa2enPwy+hfiKaH6B0sqcp8KU3E2UEB70o="
        }
      },
      "9": {
        "private": {
          "type": "Buffer",
          "data": "6HzA/Bgapb+qu+tXmW4Z8t2NZVjtmr7qvpIBc6b7+1E="
        },
        "public": {
          "type": "Buffer",
          "data": "G3oOYqYuMTGMvVRo4s7oGtdyL0mi5zwRLgBaFjNMxh8="
        }
      },
      "10": {
        "private": {
          "type": "Buffer",
          "data": "UD3BWde0froJQmabSqTXJzsOgok2/XDmx2zTPef0o1c="
        },
        "public": {
          "type": "Buffer",
          "data": "NbZtGHDDAE5affGfEQDUMJlVIQI7Ut+cJ+H9EASBxXM="
        }
      },
      "11": {
        "private": {
          "type": "Buffer",
          "data": "+DKtYD6LdVH1SFfMiiX5fevDmprElUqOuP/Mr3t4gFE="
        },
        "public": {
          "type": "Buffer",
          "data": "56RtPPnXj38Ae/ziV1Dq24J2ET7p5tUN6+ShVgtNjkc="
        }
      },
      "12": {
        "private": {
          "type": "Buffer",
          "data": "WJdnOqes9kakPOXbmS0t0TzzEYAyrTk5J+deXzWNcUE="
        },
        "public": {
          "type": "Buffer",
          "data": "u8N1baiZfs/lxazgMtA9Vm+rxTAWrdGd+Qu+wTvGRB4="
        }
      },
      "13": {
        "private": {
          "type": "Buffer",
          "data": "CHiSYkSdG9iaf5hND0GJLvqaNxGfi+5Azo6BbtY7q1k="
        },
        "public": {
          "type": "Buffer",
          "data": "OV3LC/T5a2HLWywNxzLsTCYNyxfHA0KYNCrQZ3raDlc="
        }
      },
      "14": {
        "private": {
          "type": "Buffer",
          "data": "UD0sRF4SXWZWPNvoF5Ud87o6yXyBgP8S/8TSD3Qe/38="
        },
        "public": {
          "type": "Buffer",
          "data": "h4RPQNffnOB6kOezs1gLvtE6e4QgXm8VU+lB/lZNiAg="
        }
      },
      "15": {
        "private": {
          "type": "Buffer",
          "data": "EFVQMU3nwJXB3Cgrot2gmjuqeED/HQ3oSy3k2msbalI="
        },
        "public": {
          "type": "Buffer",
          "data": "RhDM8Fk/HXmxRvmTS5X1nbdhOmXZpn+ksKhYoWI+fS4="
        }
      },
      "16": {
        "private": {
          "type": "Buffer",
          "data": "ACJlb26jncPGmV/2Ppvb6ckIICctbZxILWm7Bcjwc0A="
        },
        "public": {
          "type": "Buffer",
          "data": "8eq9Si8lj6TzKx9s/5qS0EaHw7D7sW/wMO7Wl7qtSzM="
        }
      },
      "17": {
        "private": {
          "type": "Buffer",
          "data": "0MdXm8trS5k758WOPIO5tWOUYGHQr+sGSrpWIIueMls="
        },
        "public": {
          "type": "Buffer",
          "data": "JWJp9OQLns+JFrKr037iq14bbuSIChgJ6Bs414RjAQ8="
        }
      },
      "18": {
        "private": {
          "type": "Buffer",
          "data": "aG/ZvglLyFrdjRno79IJSDfhkJSIWVXITr0RrubNOXQ="
        },
        "public": {
          "type": "Buffer",
          "data": "ZhU8yc6IIGSlWO1Gq79XFhg22YTwkoQdvgwvl8juclQ="
        }
      },
      "19": {
        "private": {
          "type": "Buffer",
          "data": "GMPptOrMufYCXDL5jCVtJna34wYZWQByRWgjzY5/oVE="
        },
        "public": {
          "type": "Buffer",
          "data": "FEk8frj9kCuEqkZCyKaqWbtqAUcWESyXxxmjgkYoQhE="
        }
      },
      "20": {
        "private": {
          "type": "Buffer",
          "data": "6KZ9EHmiOWZ4jVDc8GJGLpwDjnbFnFnnNFgiCkeZ52g="
        },
        "public": {
          "type": "Buffer",
          "data": "u1rjlPxg34dVhZvUft6tbiYYtbtQW2jBWvk5EMdzI3Y="
        }
      },
      "21": {
        "private": {
          "type": "Buffer",
          "data": "wHMyYjU2ZfFX3Qpl/eqFpT+V6yMQmB30FlKGiZjbPUc="
        },
        "public": {
          "type": "Buffer",
          "data": "DKZe6YUI/vQh5bbfhgG8cO9qbvpaB1zu18w8qVjxLn4="
        }
      },
      "22": {
        "private": {
          "type": "Buffer",
          "data": "8FAEhtW5GVVPNh5N8y9WF1usxBDt7FwQbNTh0+uSWUg="
        },
        "public": {
          "type": "Buffer",
          "data": "dgGH5qWMPfyeuKOrhF5jW7WLKtyXWvyojPdE2E1QjCs="
        }
      },
      "23": {
        "private": {
          "type": "Buffer",
          "data": "OIkv4OXSaDtDOcjGstAylbm/8NpN9LudK6PGRMIqQ1M="
        },
        "public": {
          "type": "Buffer",
          "data": "xFNfBRElxucyT6RDx2mLA4IJr/8mz2JrRV5R0Q74yRo="
        }
      },
      "24": {
        "private": {
          "type": "Buffer",
          "data": "QPjTMRXuPZ1TOhE71YR+wbn9HdBn2KTFrWpNQp7Q+EE="
        },
        "public": {
          "type": "Buffer",
          "data": "lUsxZFu7JukY/kzpAwe7RPll40NfilHttUEXXTdBGQk="
        }
      },
      "25": {
        "private": {
          "type": "Buffer",
          "data": "MA1AwhUrdEENqHv1sTNIl4hEvgqGGfsA2UhodwNCCXI="
        },
        "public": {
          "type": "Buffer",
          "data": "NqaARRIvYuslqLqAh7U0qjlilUDswXpG3C/SVpgk9wg="
        }
      },
      "26": {
        "private": {
          "type": "Buffer",
          "data": "eDVReoW3b+vIr7SzUpifxUMBqf0Kf/NDIN0Dt6lxumQ="
        },
        "public": {
          "type": "Buffer",
          "data": "VxNlq4CX/pqBnwaZK1Kl0S2Qgl3MqBS54bBuKt39sFE="
        }
      },
      "27": {
        "private": {
          "type": "Buffer",
          "data": "CPCKrhhNlZNYdilLQMS3nPW3Zi89ri15s9b29qHrelc="
        },
        "public": {
          "type": "Buffer",
          "data": "2gKVcZ1egkJCQwz4+hzFPzaEO3EXaNvvhxvTohcLR2Y="
        }
      },
      "28": {
        "private": {
          "type": "Buffer",
          "data": "6H+JWLpog9NqUxHV70kz17xp3tcf6Bbr9vbpotiYfmg="
        },
        "public": {
          "type": "Buffer",
          "data": "AESAtDRCfLiIVxOQ6T5MadlrTU4V91WNu3uVaao+WRE="
        }
      },
      "29": {
        "private": {
          "type": "Buffer",
          "data": "gLJf1MAzMHEir7jzLVuMZJRUH5XJTvOb2SOuS0FH/Es="
        },
        "public": {
          "type": "Buffer",
          "data": "3qwWr9mm60FTBEfYdEAV39TwR/+n/Lz24vjuyRJImgM="
        }
      },
      "30": {
        "private": {
          "type": "Buffer",
          "data": "gHlKw7VjVK+kh1iSDL4TeqJ83uC9ibHxea+flpZteWo="
        },
        "public": {
          "type": "Buffer",
          "data": "ltMp/3bc/SiQCVpvdzcTr1MUmgfOwAo47EbWHC9ev1Y="
        }
      }
    },
    "sessions": {
      "6282122365620.0": {
        "_sessions": {
          "BYE3MyeS8cL/dSBSgQvpd6P3oHf7crSVEBtRcGuyFQ8t": {
            "registrationId": 495190629,
            "currentRatchet": {
              "ephemeralKeyPair": {
                "pubKey": "Bb9ZaGQXv1Dhv3WK28K6IioHDqTfbKyEuC3OM0ewo818",
                "privKey": "kJscVsjbY+gRwjjvKiReofJpwFy5M0OEiTOEPUL0W0c="
              },
              "lastRemoteEphemeralKey": "BdLwNjRE7XyN07Kcf6X9p6L3+Iugithkaz1P3OyER1If",
              "previousCounter": 0,
              "rootKey": "luGIapcEhtI4VGjQxw/k+Vs8UGvO7o+q/rlKBOhrRXQ="
            },
            "indexInfo": {
              "baseKey": "BYE3MyeS8cL/dSBSgQvpd6P3oHf7crSVEBtRcGuyFQ8t",
              "baseKeyType": 2,
              "closed": -1,
              "used": 1662003242176,
              "created": 1662003242176,
              "remoteIdentityKey": "Ba2qXbuozI8Te0K4CSRlxV2QPj+hkxl+Wi1TVfyMqk0r"
            },
            "_chains": {
              "BdLwNjRE7XyN07Kcf6X9p6L3+Iugithkaz1P3OyER1If": {
                "chainKey": {
                  "counter": 7,
                  "key": "ffRJJWimNnJJzG7s3bEfYNyEEU/9KpdvvdnwtFZJblw="
                },
                "chainType": 2,
                "messageKeys": {}
              },
              "Bb9ZaGQXv1Dhv3WK28K6IioHDqTfbKyEuC3OM0ewo818": {
                "chainKey": {
                  "counter": -1,
                  "key": "4IQX+KQIjdxeMXs4iSKnEc7PmrCzhdmYw81rorLUgwY="
                },
                "chainType": 1,
                "messageKeys": {}
              }
            }
          }
        },
        "version": "v1"
      }
    },
    "appStateSyncKeys": {
      "AAAAANl+": {
        "keyData": "Pe6etkG03N+/9D6QjOuIdw1jPxnEiL4WSWI1ePdrpPY=",
        "fingerprint": {
          "rawId": 14028659,
          "currentIndex": 1,
          "deviceIndexes": [
            0,
            1
          ]
        },
        "timestamp": "0"
      },
      "AAAAANl/": {
        "keyData": "VSMRlmm4/MYD0XHnMGXNdV5yF4hHEUY/hcSDscIYO3I=",
        "fingerprint": {
          "rawId": 14028659,
          "currentIndex": 1,
          "deviceIndexes": [
            0
          ]
        },
        "timestamp": "1661994041378"
      },
      "AAAAANmC": {
        "keyData": "EbidByWpZ6oA/qm1w+Ef64AjBelWcRK+wqdkfDIctYo=",
        "fingerprint": {
          "rawId": 14028661,
          "currentIndex": 1,
          "deviceIndexes": [
            0,
            1
          ]
        },
        "timestamp": "0"
      },
      "AAAAANmD": {
        "keyData": "k9HQABVkeilUZbZG552xDcnZOQFjOWJkjD6wUsClUo4=",
        "fingerprint": {
          "rawId": 14028661,
          "currentIndex": 1,
          "deviceIndexes": [
            0
          ]
        },
        "timestamp": "1662001336628"
      },
      "AAAAANmA": {
        "keyData": "VGzBXDYAVLUM6IvWxF/KQxV04R05e+MRwFnkYzQiUaw=",
        "fingerprint": {
          "rawId": 14028660,
          "currentIndex": 1,
          "deviceIndexes": [
            0,
            1
          ]
        },
        "timestamp": "0"
      },
      "AAAAANmB": {
        "keyData": "mjm8L1jKqP5rmdMdOuJ+A4YBaIXWjszv2npnQwAXedg=",
        "fingerprint": {
          "rawId": 14028660,
          "currentIndex": 1,
          "deviceIndexes": [
            0
          ]
        },
        "timestamp": "1661996121131"
      },
      "AAAAANmE": {
        "keyData": "ABpcLLk3b+8in54cciUaPMddn+moxHQfghvO1wPvqY4=",
        "fingerprint": {
          "rawId": 14028662,
          "currentIndex": 1,
          "deviceIndexes": [
            0,
            1
          ]
        },
        "timestamp": "1662003244234"
      }
    },
    "appStateVersions": {
      "regular": {
        "version": 15,
        "hash": {
          "type": "Buffer",
          "data": "iQNNIZcV2Q2SxRRJ5tgXBl+0E/yzsNGAXyVLTH1Tjrts4rTn+Dfk9j/G9RcgV+Rw21tA5RENqoVYDXyqUliitsfS6blmPqCSAP3cuJRk6pH196ZEA5a3bKtlsjyzqnbtJu9w64ASsxn6KzNmHBzzm6PXVKzHRPFUo5kQE2z0R6g="
        },
        "indexValueMap": {
          "0JaFFjQpY57KBVFHaExjOgsmmsAVptNLdLw5jgCzpyo=": {
            "valueMac": {
              "type": "Buffer",
              "data": "Aq8NNSaon2xZnLh3gxXGOaDY5KFoze9Plr7oSl0qRMI="
            }
          },
          "0bTGhYN6Nfa4GwdfaWfazWuCTu0coaSCX9peSrmHkC0=": {
            "valueMac": {
              "type": "Buffer",
              "data": "t6fbVnIQUoJ02CSKYeycz/itGTSfzJxzzw6AWigNiHU="
            }
          },
          "uEIkfMt760YNRJAWfT0TdxZu8HNtRf/QwskP8OBcrg4=": {
            "valueMac": {
              "type": "Buffer",
              "data": "zMPE11vZ99dLiDPtgtAzNNlvX5H4JRHKNqpIeSCvphA="
            }
          },
          "k+vw7cMJK6K5mOQv66j7JeIff31holi5Uckic1Rxvoc=": {
            "valueMac": {
              "type": "Buffer",
              "data": "8KtPAqsjzzAqXGu2v40fPkZF9iBibcmK8U54UVVKcfc="
            }
          },
          "rf+r7uTnO12EM5XcpqZlG3WjJ1425pocf3WtAOKaLNo=": {
            "valueMac": {
              "type": "Buffer",
              "data": "rY7xOEHx6HogBotMIHHAmLJDGZUgloV+hnKhNh1dv0s="
            }
          },
          "ktJarajOyqJe65W57bb3uObX3I8+o+KUy6f4txw5DZE=": {
            "valueMac": {
              "type": "Buffer",
              "data": "zQHfdufFfO5ulp8/D914aDA1K1HH02Rf6tKXA2dNjuU="
            }
          },
          "NZaQhN6/f/jGpzUk5Sun3dy/Fe+FLn28fOkjPviTk58=": {
            "valueMac": {
              "type": "Buffer",
              "data": "nGYQq9CgP2QQBtKCxLoKOh9cEqoa+3vOlPA2ggMtCb4="
            }
          },
          "6dVE7EcZt5rdQLUGmsRJ9+xkKCYS95JxdqjxWpmOdJo=": {
            "valueMac": {
              "type": "Buffer",
              "data": "yyhFdNLVPO8HXYtr6Nq2gKHbue6wnLBdBvTKZdn0MAE="
            }
          },
          "++1svtJ3+zX/3ceyYgzwQV3yGJyli0OT5JxfuzkhT+Q=": {
            "valueMac": {
              "type": "Buffer",
              "data": "af/y2qQId1mikzaB+Z2L3ENNOXC6go2Qmag3WcdYGPg="
            }
          },
          "uw6ddj8hyqs0UoB9KsYVPS9jPaGTBwkDAPmRtJW6zA4=": {
            "valueMac": {
              "type": "Buffer",
              "data": "A2CnKVVn2hhIJPagXnolaG08/Kpu8DCwlTZ9dtr8gtg="
            }
          },
          "7ZN2gc5nL1bkJHQien0TVtdmRbjQTPbopxLKwIpfxdQ=": {
            "valueMac": {
              "type": "Buffer",
              "data": "zgXimcekIaeNaW1W+FAXbWHSKcl5Pjhq5ciVknxo+Xw="
            }
          }
        }
      }
    }
  }
}